LICENSE
README.md
pyproject.toml
src/python_wheel.egg-info/PKG-INFO
src/python_wheel.egg-info/SOURCES.txt
src/python_wheel.egg-info/dependency_links.txt
src/python_wheel.egg-info/top_level.txt
src/wheel/__init__.py