Metadata-Version: 2.1
Name: python-wheel
Version: 0.0.4.0
Summary: This is a sham PyPI package creation. In fact, it should be considered malicious. It was a naive
Author-email: Kale Franz <eetygr@gmail.com>
Project-URL: Homepage, https://github.com/kalefranz/python-wheel
Classifier: Programming Language :: Python :: 3
Classifier: License :: OSI Approved :: MIT License
Classifier: Operating System :: OS Independent
Requires-Python: >=3.7
License-File: LICENSE
